aiml/__init__.py
aiml/__main__.py
auto_aiml-1.0.4.dist-info/LICENSE
auto_aiml-1.0.4.dist-info/METADATA
auto_aiml-1.0.4.dist-info/WHEEL
auto_aiml-1.0.4.dist-info/entry_points.txt
auto_aiml-1.0.4.dist-info/top_level.txt
auto_aiml-1.0.4.dist-info/RECORD
