Metadata-Version: 2.1
Name: auto-aiml
Version: 1.0.4
Summary: Creates a best predictive regression/classification model 
Home-page: https://github.com/yashu7890/yash
Author: Yashwanth Agastya
Author-email: admin@yash.com
License: MIT
Platform: UNKNOWN
Classifier: License :: OSI Approved :: MIT License
Classifier: Programming Language :: Python :: 3.6
Classifier: Programming Language :: Python :: 3.7
Classifier: Programming Language :: Python :: 3.8
License-File: LICENSE
Requires-Dist: numpy
Requires-Dist: pandas
Requires-Dist: scipy
Requires-Dist: sklearn
Requires-Dist: imblearn
Requires-Dist: xgboost
